pychk/__init__.py
pychk/check_deps.py
pychk/custom_parser.py
pychk/fetch_resources.py
pychk/file_management.py
pychk/main.py
pychk-1.0.1.dist-info/LICENSE
pychk-1.0.1.dist-info/METADATA
pychk-1.0.1.dist-info/WHEEL
pychk-1.0.1.dist-info/entry_points.txt
pychk-1.0.1.dist-info/top_level.txt
pychk-1.0.1.dist-info/RECORD
