Metadata-Version: 2.1
Name: pychk
Version: 1.0.1
Summary: A command line tool for developers to check if their project dependencies have known vulnerabilities.
Home-page: https://github.com/ayushpriya10/pychk
Author: Ayush Priya
Author-email: ayushpriya10@gmail.com
License: UNKNOWN
Keywords: pip requirements security SAST sast vulnerability dependencies dependency vulnerable
Platform: UNKNOWN
Classifier: Development Status :: 4 - Beta
Classifier: License :: OSI Approved :: MIT License 
Classifier: Programming Language :: Python :: 3.6
Requires-Python: >=3.6
Requires-Dist: argparse
Requires-Dist: packaging
Requires-Dist: requests
